jumpstarter_driver_shell/__init__.py
jumpstarter_driver_shell/client.py
jumpstarter_driver_shell/driver.py
jumpstarter_driver_shell/driver_test.py
jumpstarter_driver_shell-0.7.4.dist-info/METADATA
jumpstarter_driver_shell-0.7.4.dist-info/WHEEL
jumpstarter_driver_shell-0.7.4.dist-info/entry_points.txt
jumpstarter_driver_shell-0.7.4.dist-info/RECORD
